simplesingletable/__init__.py
simplesingletable/blob_storage.py
simplesingletable/dynamodb_memory.py
simplesingletable/models.py
simplesingletable/transactions.py
simplesingletable/utils.py
simplesingletable/extras/__init__.py
simplesingletable/extras/audit.py
simplesingletable/extras/form_data.py
simplesingletable/extras/habit_tracker.py
simplesingletable/extras/readonly_repository.py
simplesingletable/extras/readonly_versioned_repository.py
simplesingletable/extras/repository.py
simplesingletable/extras/singleton.py
simplesingletable/extras/versioned_repository.py
simplesingletable-16.1.0.dist-info/LICENSE
simplesingletable-16.1.0.dist-info/METADATA
simplesingletable-16.1.0.dist-info/WHEEL
simplesingletable-16.1.0.dist-info/top_level.txt
simplesingletable-16.1.0.dist-info/RECORD
