Metadata-Version: 2.1
Name: simplesingletable
Version: 16.1.0
Summary: A simple boto3/Pydantic implementation of DynamoDB Single Table Design and related utilities.
Author-email: Sully <sully@sadburger.com>
License: MIT
Project-URL: Homepage, https://github.com/msull/simplesingletable
Keywords: dynamodb,singletabledesign
Classifier: Programming Language :: Python
Classifier: Programming Language :: Python :: 3
Requires-Python: >=3.10
License-File: LICENSE
Requires-Dist: boto3
Requires-Dist: humanize
Requires-Dist: pydantic>2
Requires-Dist: ulid-py
Provides-Extra: build
Requires-Dist: build; extra == "build"
Requires-Dist: twine; extra == "build"
Provides-Extra: dev
Requires-Dist: black; extra == "dev"
Requires-Dist: boto3-stubs[dynamodb]; extra == "dev"
Requires-Dist: bumpver; extra == "dev"
Requires-Dist: invoke; extra == "dev"
Requires-Dist: isort; extra == "dev"
Requires-Dist: logzero; extra == "dev"
Requires-Dist: pip-tools; extra == "dev"
Requires-Dist: pytest; extra == "dev"
Requires-Dist: pytest-cov; extra == "dev"
Requires-Dist: pytest-docker; extra == "dev"
Requires-Dist: pytest-mock; extra == "dev"
Requires-Dist: ruff; extra == "dev"
Requires-Dist: streamlit; extra == "dev"
Requires-Dist: streamlit-extras; extra == "dev"
Requires-Dist: tabulate; extra == "dev"
Requires-Dist: watchdog; extra == "dev"
